vtk.py
vtkmodules/__init__.py
vtkmodules/all.py
vtkmodules/generate_pyi.py
vtkmodules/sqlitebin-9.2.exe
vtkmodules/sqlitebin-9.2.exe.manifest
vtkmodules/vtkChartsCore-9.2.dll
vtkmodules/vtkChartsCore-9.2.dll.manifest
vtkmodules/vtkChartsCore.pyd
vtkmodules/vtkCommonColor-9.2.dll
vtkmodules/vtkCommonColor-9.2.dll.manifest
vtkmodules/vtkCommonColor.pyd
vtkmodules/vtkCommonComputationalGeometry-9.2.dll
vtkmodules/vtkCommonComputationalGeometry-9.2.dll.manifest
vtkmodules/vtkCommonComputationalGeometry.pyd
vtkmodules/vtkCommonCore-9.2.dll
vtkmodules/vtkCommonCore-9.2.dll.manifest
vtkmodules/vtkCommonCore.pyd
vtkmodules/vtkCommonDataModel-9.2.dll
vtkmodules/vtkCommonDataModel-9.2.dll.manifest
vtkmodules/vtkCommonDataModel.pyd
vtkmodules/vtkCommonExecutionModel-9.2.dll
vtkmodules/vtkCommonExecutionModel-9.2.dll.manifest
vtkmodules/vtkCommonExecutionModel.pyd
vtkmodules/vtkCommonMath-9.2.dll
vtkmodules/vtkCommonMath-9.2.dll.manifest
vtkmodules/vtkCommonMath.pyd
vtkmodules/vtkCommonMisc-9.2.dll
vtkmodules/vtkCommonMisc-9.2.dll.manifest
vtkmodules/vtkCommonMisc.pyd
vtkmodules/vtkCommonPython-9.2.dll
vtkmodules/vtkCommonPython-9.2.dll.manifest
vtkmodules/vtkCommonPython.pyd
vtkmodules/vtkCommonSystem-9.2.dll
vtkmodules/vtkCommonSystem-9.2.dll.manifest
vtkmodules/vtkCommonSystem.pyd
vtkmodules/vtkCommonTransforms-9.2.dll
vtkmodules/vtkCommonTransforms-9.2.dll.manifest
vtkmodules/vtkCommonTransforms.pyd
vtkmodules/vtkDICOMParser-9.2.dll
vtkmodules/vtkDICOMParser-9.2.dll.manifest
vtkmodules/vtkDomainsChemistry-9.2.dll
vtkmodules/vtkDomainsChemistry-9.2.dll.manifest
vtkmodules/vtkDomainsChemistry.pyd
vtkmodules/vtkDomainsChemistryOpenGL2-9.2.dll
vtkmodules/vtkDomainsChemistryOpenGL2-9.2.dll.manifest
vtkmodules/vtkDomainsChemistryOpenGL2.pyd
vtkmodules/vtkFiltersAMR-9.2.dll
vtkmodules/vtkFiltersAMR-9.2.dll.manifest
vtkmodules/vtkFiltersAMR.pyd
vtkmodules/vtkFiltersCore-9.2.dll
vtkmodules/vtkFiltersCore-9.2.dll.manifest
vtkmodules/vtkFiltersCore.pyd
vtk_onepoint-9.2.2.20230614.dev0.dist-info/LICENSE
vtk_onepoint-9.2.2.20230614.dev0.dist-info/METADATA
vtk_onepoint-9.2.2.20230614.dev0.dist-info/WHEEL
vtk_onepoint-9.2.2.20230614.dev0.dist-info/top_level.txt
vtk_onepoint-9.2.2.20230614.dev0.dist-info/RECORD
