Metadata-Version: 2.1
Name: vtk-onepoint
Version: 9.2.2.20230614.dev0
Summary: VTK is an open-source toolkit for 3D computer graphics, image processing, and visualization
Home-page: https://vtk.org
Download-URL: https://vtk.org/download/
Author: VTK developers
License: BSD
Platform: UNKNOWN
Classifier: License :: OSI Approved :: BSD License
Classifier: Programming Language :: Python
Classifier: Programming Language :: C++
Classifier: Intended Audience :: Developers
Classifier: Intended Audience :: Education
Classifier: Intended Audience :: Healthcare Industry
Classifier: Intended Audience :: Science/Research
Classifier: Topic :: Multimedia :: Graphics
Classifier: Topic :: Multimedia :: Graphics :: 3D Modeling
Classifier: Topic :: Multimedia :: Graphics :: 3D Rendering
Classifier: Topic :: Scientific/Engineering
Classifier: Topic :: Scientific/Engineering :: Chemistry
Classifier: Topic :: Scientific/Engineering :: Information Analysis
Classifier: Topic :: Scientific/Engineering :: Medical Science Apps.
Classifier: Topic :: Scientific/Engineering :: Physics
Classifier: Topic :: Scientific/Engineering :: Visualization
Classifier: Topic :: Software Development :: Libraries
Classifier: Operating System :: Microsoft :: Windows
Classifier: Operating System :: POSIX
Classifier: Operating System :: Unix
Classifier: Operating System :: MacOS
License-File: LICENSE
Provides-Extra: gtk
Provides-Extra: numpy
Requires-Dist: numpy (>=1.9) ; extra == 'numpy'
Provides-Extra: qt
Provides-Extra: rendering
Provides-Extra: rendering-backend-gl
Provides-Extra: rendering-onscreen
Provides-Extra: rendering-onscreen-windows
Provides-Extra: tk
Provides-Extra: wx
